{"split": "dev", "seed": 1, "per_suite": 150, "vector": [true, true, true, true, true, true, true, true, true, true, true, true, true, true, true, true, true, true, true, false, true, true, true, true, false, true, true, true, false, true, true, true, true, true, true, true, true, true, false, true, true, true, true, false, true, true, true, true, true, false, true, true, true, true, true, true, true, true, true, true, true, false, true, true, true, true, true, true, true, true, true, true, true, true, true, true, true, true, true, true, true, true, true, true, true, true, true, true, true, true, true, true, true, true, true, true, true, true, true, true, true, true, true, true, true, true, true, true, true, true, true, true, true, true, true, true, true, false, true, true, true, true, true, true, true, true, true, true, true, false, true, true, true, true, true, true, true, true, true, true, true, true, true, true, true, true, true, true, true, true, true, true, true, true, true, true, true, true, true, true, true, true, true, true, true, true, true, true, true, true, true, true, true, false, true, true, true, true, true, true, true, true, true, true, true, true, true, false, true, true, true, true, false, true, true, true, true, true, true, true, true, true, false, true, true, false, true, true, true, true, true, true, true, true, true, true, true, true, true, true, true, true, true, false, true, true, true, true, true, true, true, false, true, true, true, true, true, false, true, true, true, true, true, true, true, true, true, false, true, true, true, true, true, true, true, true, true, true, false, true, true, true, true, true, true, true, true, true, true, true, true, true, true, true, true, true, true, true, true, true, true, true, true, true, true, true, true, true, true, true, true, true, true, true, false, true, true, true, true, true, true, true, true, true, true, true, true, true, true, true, true, true, true, true, true, true, true, true, true, true, true, true, true, true, true, true, true, false, true, true, true, true, true, true, true, true, true, true, true, true, true, true, true, true, true, false, true, true, true, true, true, true, true, true, true, true, true, true, true, true, true, true, true, true, true, true, true, true, true, true, true, true, true, true, true, true, true, true, true, true, false, true, true, true, true, true, true, true, true, true, true, true, false, true, true, true, true, true, true, true, false, true, true, false, true, true, true, true, true, true, true, true, true, true, true, true, true, true, true, true, true, true, false, true, true, true, true, true, true, true, true, true, true, false, true, true, true, true, true, true, true, true, true, true, false, false, true, true, true, true], "axes": {"accuracy": 0.9333333333333332, "per_suite": {"reasoning": 0.9333333333333333, "math": 0.9266666666666666, "code_qa": 0.94}, "cost_per_task": 0.03841688888888889, "latency_p50_ms": 0.3131170087726787}}